<?xml version="1.0" encoding="UTF-8"?>
<assets PGFVersion="0.20" GSCVersion="0.11.0.13"><sounds/><images><image name="Home"><file premulAlpha="0" name="Home.png" size="75361"/></image><image name="Map"><file premulAlpha="0" name="Map.png" size="117095"/></image><image name="China"><file premulAlpha="0" name="China.png" size="691543"/></image><image name="China_Sign1"><file premulAlpha="0" name="China_Sign1.png" size="96420"/></image><image name="Good_job"><file premulAlpha="0" name="Good_job.png" size="125127"/></image><image name="bust"><file name="bust.png"/></image><image name="Splash Page"><file premulAlpha="0" name="Splash Page.png" size="1168394"/></image><image name="Instructions"><file premulAlpha="0" name="Instructions.png" size="1192102"/></image><image name="Back Button"><file premulAlpha="0" name="Back Button.png" size="22160"/></image><image name="Bottom Bar"><file premulAlpha="0" name="Bottom Bar.png" size="21859"/></image><image name="Delivery Sign"><file premulAlpha="0" name="Delivery Sign.png" size="8175"/></image><image name="Temple Bell Delivery"><file premulAlpha="0" name="Temple Bell Delivery.png" size="101335"/></image><image name="Japan"><file premulAlpha="0" name="Japan.png" size="567865"/></image><image name="Korea"><file premulAlpha="0" name="Korea.png" size="695019"/></image><image name="Canada"><file premulAlpha="0" name="Canada.png" size="666506"/></image><image name="China 1 Delivery Sign"><file premulAlpha="0" name="China 1 Delivery Sign.png" size="7568"/></image><image name="Temple Bell"><file premulAlpha="0" name="Temple Bell.png" size="152316"/></image><image name="The Death of General Wolfe"><file premulAlpha="0" name="The Death of General Wolfe.png" size="75416"/></image><image name="Canada 1 Delivery Sign"><file premulAlpha="0" name="Canada 1 Delivery Sign.png" size="11628"/></image><image name="The Death of General Wolfe On Wall"><file premulAlpha="0" name="The Death of General Wolfe On Wall.png" size="50087"/></image><image name="The Death of General Wolfe Delivery"><file premulAlpha="0" name="The Death of General Wolfe Delivery.png" size="107856"/></image></images><behaviors/></assets>
